[
  {
    "room": "eileen",
    "time": "2024-06-12T19:20:00Z",
    "type": "0",
    "desc": "小琳的秘密备忘录~"
  },
  {
    "room": "diana",
    "time": "2024-06-12T20:50:00Z",
    "type": "0",
    "desc": "嘉然的社交方法论"
  },
  {
    "room": "bella",
    "time": "2024-06-13T19:20:00Z",
    "type": "0",
    "desc": "贝拉的灵异小剧场"
  },
  {
    "room": "eileen",
    "time": "2024-06-13T20:50:00Z",
    "type": "0",
    "desc": "台词大挑战!"
  },
  {
    "room": "diana",
    "time": "2024-06-14T19:50:00Z",
    "type": "1",
    "desc": "再战女鬼桥2！"
  },
  {
    "room": "bella",
    "time": "2024-06-16T19:50:00Z",
    "type": "1",
    "desc": "谁是森林之王!!!"
  }
]